iteru/__init__.py
iteru/common.py
iteru/iterugee.py
iteru/map.py
iteru-0.0.45.dist-info/LICENSE
iteru-0.0.45.dist-info/METADATA
iteru-0.0.45.dist-info/WHEEL
iteru-0.0.45.dist-info/dependency_links.txt
iteru-0.0.45.dist-info/top_level.txt
iteru-0.0.45.dist-info/RECORD
