Metadata-Version: 2.1
Name: iteru
Version: 0.0.45
Summary: Python package for a web app
Home-page: https://github.com/MuhammedM294/iteru
Author: Muhammed Abdelaal
Author-email: muhammedaabdelaal@gmail.com
License: MIT license
Keywords: iteru
Classifier: Development Status :: 2 - Pre-Alpha
Classifier: Intended Audience :: Developers
Classifier: License :: OSI Approved :: MIT License
Classifier: Natural Language :: English
Classifier: Programming Language :: Python :: 3
Classifier: Programming Language :: Python :: 3.5
Classifier: Programming Language :: Python :: 3.6
Classifier: Programming Language :: Python :: 3.7
Classifier: Programming Language :: Python :: 3.8
Requires-Python: >=3.5
License-File: LICENSE
Requires-Dist: earthengine-api
Requires-Dist: ipyleaflet
Requires-Dist: ipywidgets
Requires-Dist: geemap
Requires-Dist: gcloud
